blofin/__init__.py
blofin/auth.py
blofin/client.py
blofin/constants.py
blofin/exceptions.py
blofin/utils.py
blofin/api/__init__.py
blofin/api/account.py
blofin/api/affiliate.py
blofin/api/public.py
blofin/api/trading.py
blofin/api/user.py
blofin-0.4.5.dist-info/METADATA
blofin-0.4.5.dist-info/WHEEL
blofin-0.4.5.dist-info/top_level.txt
blofin-0.4.5.dist-info/RECORD
